kubepy/__init__.py
kubepy/api.py
kubepy/appliers.py
kubepy/appliers_options.py
kubepy/base_commands.py
kubepy/definition_manager.py
kubepy/definition_merger.py
kubepy/definition_transformers.py
kubepy/commands/__init__.py
kubepy/commands/apply_all.py
kubepy/commands/apply_one.py
kubepy-1.20.0.dist-info/LICENSE
kubepy-1.20.0.dist-info/METADATA
kubepy-1.20.0.dist-info/WHEEL
kubepy-1.20.0.dist-info/entry_points.txt
kubepy-1.20.0.dist-info/top_level.txt
kubepy-1.20.0.dist-info/RECORD
