Metadata-Version: 2.1
Name: kubepy
Version: 1.20.0
Summary: Python wrapper on kubectl that makes deploying easy.
Home-page: https://github.com/socialwifi/kubepy
Author: Social WiFi
Author-email: it@socialwifi.com
License: BSD
Classifier: Development Status :: 5 - Production/Stable
Classifier: Environment :: Console
Classifier: Intended Audience :: Developers
Classifier: License :: OSI Approved :: BSD License
Classifier: Operating System :: OS Independent
Classifier: Programming Language :: Python
Classifier: Programming Language :: Python :: 3
Classifier: Programming Language :: Python :: 3.9
Classifier: Programming Language :: Python :: 3.10
Classifier: Programming Language :: Python :: 3.11
Classifier: Programming Language :: Python :: 3.12
License-File: LICENSE
Requires-Dist: cached-property
Requires-Dist: PyYAML
Requires-Dist: tenacity
